{
  "KEYWORD_nearbyStations.name": "保谷",
  "took": 1,
  "timed_out": false,
  "_shards": { "total": 1, "successful": 1, "skipped": 0, "failed": 0 },
  "hits": {
    "total": { "value": 42, "relation": "eq" },
    "max_score": 10.081755,
    "hits": [
      {
        "_index": "parking",
        "_id": "1207681",
        "_score": 10.081755,
        "_source": {
          "region": { "name": "南大泉" },
          "addressView": "",
          "payment": { "fee": 0 },
          "spaces": [
            { "rent": 0, "rentMin": null, "rentTaxClass": null, "facility": 2 },
            { "rent": 0, "rentMin": null, "rentTaxClass": null, "facility": 2 }
          ],
          "capacity": 0,
          "prefecture": { "name": "東京都" },
          "city": { "name": "練馬区" },
          "referralFeeTotal": 0,
          "storageDocument": { "issuingFee": 0 },
          "address": "東京都練馬区南大泉４丁目",
          "hasDivisionDrawing": false,
          "location": { "lon": 139.573906, "lat": 35.743976 },
          "securityFacilities": [],
          "nearbyStations": [{ "name": "保谷" }]
        }
      },
      {
        "_index": "parking",
        "_id": "1210220",
        "_score": 5.3881288,
        "_source": {
          "region": { "name": "神田駿河台" },
          "addressView": "",
          "payment": { "fee": 1 },
          "spaces": [
            { "rent": 0, "rentMin": null, "rentTaxClass": null, "facility": 2 }
          ],
          "capacity": 0,
          "prefecture": { "name": "東京都" },
          "city": { "name": "千代田区" },
          "referralFeeTotal": 0,
          "storageDocument": { "issuingFee": 0 },
          "address": "東京都千代田区神田駿河台２丁目",
          "hasDivisionDrawing": false,
          "location": { "lon": 139.75967, "lat": 35.700017 },
          "securityFacilities": [],
          "nearbyStations": [
            { "name": "神保町" },
            { "name": "御茶ノ水" },
            { "name": "本郷三丁目" }
          ]
        }
      },
      {
        "_index": "parking",
        "_id": "1209524",
        "_score": 5.3881288,
        "_source": {
          "region": { "name": "北新宿" },
          "addressView": "",
          "payment": { "fee": 1 },
          "spaces": [
            { "rent": 0, "rentMin": null, "rentTaxClass": null, "facility": 2 }
          ],
          "capacity": 0,
          "prefecture": { "name": "東京都" },
          "city": { "name": "新宿区" },
          "referralFeeTotal": 0,
          "storageDocument": { "issuingFee": 0 },
          "address": "東京都新宿区北新宿３丁目",
          "hasDivisionDrawing": false,
          "location": { "lon": 139.690743, "lat": 35.702146 },
          "securityFacilities": [],
          "nearbyStations": [
            { "name": "大久保" },
            { "name": "西新宿" },
            { "name": "東中野" }
          ]
        }
      },
      {
        "_index": "parking",
        "_id": "1209537",
        "_score": 5.3881288,
        "_source": {
          "region": { "name": "北新宿" },
          "addressView": "",
          "payment": { "fee": 1 },
          "spaces": [
            { "rent": 0, "rentMin": null, "rentTaxClass": null, "facility": 2 }
          ],
          "capacity": 0,
          "prefecture": { "name": "東京都" },
          "city": { "name": "新宿区" },
          "referralFeeTotal": 0,
          "storageDocument": { "issuingFee": 0 },
          "address": "東京都新宿区北新宿１丁目",
          "hasDivisionDrawing": false,
          "location": { "lon": 139.692108, "lat": 35.698433 },
          "securityFacilities": [],
          "nearbyStations": [
            { "name": "西新宿" },
            { "name": "大久保" },
            { "name": "都庁前" }
          ]
        }
      },
      {
        "_index": "parking",
        "_id": "1209535",
        "_score": 5.080245,
        "_source": {
          "region": { "name": "百人町" },
          "addressView": "",
          "payment": { "fee": 1 },
          "spaces": [
            { "rent": 0, "rentMin": null, "rentTaxClass": null, "facility": 2 }
          ],
          "capacity": 0,
          "prefecture": { "name": "東京都" },
          "city": { "name": "新宿区" },
          "referralFeeTotal": 0,
          "storageDocument": { "issuingFee": 0 },
          "address": "東京都新宿区百人町",
          "hasDivisionDrawing": false,
          "location": { "lon": 139.69565, "lat": 35.703404 },
          "securityFacilities": [],
          "nearbyStations": [{ "name": "大久保" }, { "name": "新大久保" }]
        }
      },
      {
        "_index": "parking",
        "_id": "1208888",
        "_score": 3.8954158,
        "_source": {
          "region": { "name": "代官山町" },
          "addressView": "",
          "payment": { "fee": 1 },
          "spaces": [
            { "rent": 0, "rentMin": null, "rentTaxClass": null, "facility": 2 }
          ],
          "capacity": 0,
          "prefecture": { "name": "東京都" },
          "city": { "name": "渋谷区" },
          "referralFeeTotal": 0,
          "storageDocument": { "issuingFee": 0 },
          "address": "東京都渋谷区代官山町",
          "hasDivisionDrawing": false,
          "location": { "lon": 139.705086, "lat": 35.651933 },
          "securityFacilities": [],
          "nearbyStations": [
            { "name": "代官山" },
            { "name": "恵比寿" },
            { "name": "渋谷" }
          ]
        }
      },
      {
        "_index": "parking",
        "_id": "1208892",
        "_score": 3.8954158,
        "_source": {
          "region": { "name": null },
          "addressView": "",
          "payment": { "fee": 1 },
          "spaces": [
            { "rent": 0, "rentMin": null, "rentTaxClass": null, "facility": 2 }
          ],
          "capacity": 0,
          "prefecture": { "name": "東京都" },
          "city": { "name": "渋谷区" },
          "referralFeeTotal": 0,
          "storageDocument": { "issuingFee": 0 },
          "address": "東京都渋谷区松涛２丁目",
          "hasDivisionDrawing": false,
          "location": { "lon": 139.697778, "lat": 35.663694 },
          "securityFacilities": [],
          "nearbyStations": [{ "name": "渋谷" }, { "name": "神泉" }]
        }
      },
      {
        "_index": "parking",
        "_id": "1210274",
        "_score": 3.3927984,
        "_source": {
          "region": { "name": "赤坂" },
          "addressView": "",
          "payment": { "fee": 1 },
          "spaces": [
            { "rent": 0, "rentMin": null, "rentTaxClass": null, "facility": 2 }
          ],
          "capacity": 0,
          "prefecture": { "name": "東京都" },
          "city": { "name": "港区" },
          "referralFeeTotal": 0,
          "storageDocument": { "issuingFee": 0 },
          "address": "東京都港区赤坂１丁目",
          "hasDivisionDrawing": false,
          "location": { "lon": 139.743777, "lat": 35.669673 },
          "securityFacilities": [],
          "nearbyStations": [
            { "name": "国会議事堂前" },
            { "name": "溜池山王" },
            { "name": "神谷町" }
          ]
        }
      },
      {
        "_index": "parking",
        "_id": "1210277",
        "_score": 3.3927984,
        "_source": {
          "region": { "name": "虎ノ門" },
          "addressView": "",
          "payment": { "fee": 0 },
          "spaces": [
            { "rent": 0, "rentMin": null, "rentTaxClass": null, "facility": 2 }
          ],
          "capacity": 0,
          "prefecture": { "name": "東京都" },
          "city": { "name": "港区" },
          "referralFeeTotal": 0,
          "storageDocument": { "issuingFee": 0 },
          "address": "東京都港区虎ノ門４丁目",
          "hasDivisionDrawing": false,
          "location": { "lon": 139.743193, "lat": 35.664553 },
          "securityFacilities": [],
          "nearbyStations": [{ "name": "神谷町" }, { "name": "六本木一丁目" }]
        }
      },
      {
        "_index": "parking",
        "_id": "1210146",
        "_score": 3.3927984,
        "_source": {
          "region": { "name": "小日向" },
          "addressView": "",
          "payment": { "fee": 0 },
          "spaces": [
            { "rent": 0, "rentMin": null, "rentTaxClass": null, "facility": 2 }
          ],
          "capacity": 0,
          "prefecture": { "name": "東京都" },
          "city": { "name": "文京区" },
          "referralFeeTotal": 0,
          "storageDocument": { "issuingFee": 0 },
          "address": "東京都文京区小日向１丁目",
          "hasDivisionDrawing": false,
          "location": { "lon": 139.736886, "lat": 35.713978 },
          "securityFacilities": [],
          "nearbyStations": [{ "name": "茗荷谷" }, { "name": "江戸川橋" }]
        }
      }
    ]
  }
}
